refchecker/__init__.py
refchecker/aggregator.py
refchecker/base.py
refchecker/checker/README.md
refchecker/checker/__init__.py
refchecker/checker/alignscore/__init__.py
refchecker/checker/alignscore/alignscore.py
refchecker/checker/alignscore/alignscore_checker.py
refchecker/checker/alignscore/dataloader.py
refchecker/checker/alignscore/inference.py
refchecker/checker/alignscore/model.py
refchecker/checker/checker_base.py
refchecker/checker/checker_prompts.py
refchecker/checker/llm_checker.py
refchecker/checker/nli_checker.py
refchecker/checker/repc/general.py
refchecker/checker/repc/ml_models.py
refchecker/checker/repc/repc_checker.py
refchecker/cli.py
refchecker/extractor/README.md
refchecker/extractor/__init__.py
refchecker/extractor/extractor_base.py
refchecker/extractor/extractor_prompts.py
refchecker/extractor/llm_extractor.py
refchecker/localizer/__init__.py
refchecker/localizer/embed_localizer.py
refchecker/retriever/__init__.py
refchecker/retriever/google_retriever.py
refchecker/utils.py
refchecker-0.2.17.dist-info/LICENSE
refchecker-0.2.17.dist-info/METADATA
refchecker-0.2.17.dist-info/NOTICE
refchecker-0.2.17.dist-info/WHEEL
refchecker-0.2.17.dist-info/entry_points.txt
refchecker-0.2.17.dist-info/RECORD
