Metadata-Version: 2.3
Name: refchecker
Version: 0.2.17
Summary: RefChecker provides automatic checking pipeline for detecting fine-grained hallucinations generated by Large Language Models.
License: Apache-2.0
Author: Xiangkun Hu
Author-email: xiangkhu@amazon.com
Requires-Python: >=3.10,<4.0
Classifier: License :: OSI Approved :: Apache Software License
Classifier: Programming Language :: Python :: 3
Classifier: Programming Language :: Python :: 3.10
Classifier: Programming Language :: Python :: 3.11
Classifier: Programming Language :: Python :: 3.12
Classifier: Programming Language :: Python :: 3.13
Provides-Extra: open-extractor
Provides-Extra: repcex
Requires-Dist: accelerate (>=0.31,<0.32)
Requires-Dist: anthropic (>=0.29,<0.30)
Requires-Dist: beautifulsoup4 (>=4.12,<5.0)
Requires-Dist: boto3 (>=1.35,<2.0)
Requires-Dist: diskcache (>=5,<6)
Requires-Dist: litellm (>=1.49,<2.0)
Requires-Dist: nltk (>=3.8,<4.0)
Requires-Dist: plotly (>=5.22,<6.0)
Requires-Dist: pytorch_lightning (>=2.3,<3.0)
Requires-Dist: rank-bm25 (>=0.2,<0.3)
Requires-Dist: scikit-learn (>=1.5,<2.0)
Requires-Dist: scikit-learn-intelex (>=2024.1.0,<2025.0.0) ; extra == "repcex"
Requires-Dist: spacy (>=3.7,<4.0)
Requires-Dist: torch (>=2,<3)
Requires-Dist: transformers (>=4.41,<5.0)
Requires-Dist: vllm (>=0.5,<0.6) ; extra == "open-extractor"
